{
  "post": [
    {
      "author": "최은석",
      "comments": [],
      "description": "",
      "id": "0c3e460f-466b-4e1a-9e48-940289075506",
      "image": {
        "breeds": [
          {
            "weight": {
              "imperial": "32 - 40",
              "metric": "15 - 18"
            },
            "height": {
              "imperial": "12.5 - 14",
              "metric": "32 - 36"
            },
            "id": 120,
            "name": "Glen of Imaal Terrier",
            "bred_for": "Rid the home and farm of vermin, and hunt badger and fox",
            "breed_group": "Terrier",
            "life_span": "12 - 15 years",
            "temperament": "Spirited, Agile, Loyal, Gentle, Active, Courageous",
            "reference_image_id": "H1oLMe94m"
          }
        ],
        "id": "H1oLMe94m",
        "url": "https://cdn2.thedogapi.com/images/H1oLMe94m_390x256.jpg",
        "width": 645,
        "height": 380
      },
      "title": "",
      "like": 0
    },
    {
      "author": "최은석",
      "comments": [],
      "description": "",
      "id": "d809e9c4-bda4-451c-a693-a150dab07803",
      "image": {
        "breeds": [
          {
            "weight": {
              "imperial": "45 - 60",
              "metric": "20 - 27"
            },
            "height": {
              "imperial": "18 - 20",
              "metric": "46 - 51"
            },
            "id": 79,
            "name": "Chinese Shar-Pei",
            "bred_for": "Fighting",
            "breed_group": "Non-Sporting",
            "life_span": "10 years",
            "temperament": "Suspicious, Affectionate, Devoted, Reserved, Independent, Loving",
            "reference_image_id": "B1ruWl94Q"
          }
        ],
        "id": "B1ruWl94Q",
        "url": "https://cdn2.thedogapi.com/images/B1ruWl94Q_390x256.jpg",
        "width": 1049,
        "height": 761
      },
      "title": "",
      "like": 0
    },
    {
      "author": "최은석",
      "comments": [],
      "description": "",
      "id": "9b665ab5-49fc-49ee-8fa8-808cfa91b039",
      "image": {
        "breeds": [
          {
            "weight": {
              "imperial": "10 - 25",
              "metric": "5 - 11"
            },
            "height": {
              "imperial": "16 - 17",
              "metric": "41 - 43"
            },
            "id": 53,
            "name": "Boston Terrier",
            "bred_for": "Ratting, Companionship",
            "breed_group": "Non-Sporting",
            "life_span": "11 - 13 years",
            "temperament": "Friendly, Lively, Intelligent",
            "reference_image_id": "rkZRggqVX"
          }
        ],
        "id": "rkZRggqVX",
        "url": "https://cdn2.thedogapi.com/images/rkZRggqVX_390x256.jpg",
        "width": 1010,
        "height": 673
      },
      "title": "",
      "like": 0
    },
    {
      "author": "은돌",
      "comments": [],
      "description": "",
      "id": "d88697f4-2938-4037-9f26-4bd9564897fe",
      "image": {
        "breeds": [
          {
            "weight": {
              "imperial": "25 - 45",
              "metric": "11 - 20"
            },
            "height": {
              "imperial": "15 - 18",
              "metric": "38 - 46"
            },
            "id": 17,
            "name": "American Water Spaniel",
            "country_code": "US",
            "bred_for": "Bird flushing and retrieving",
            "breed_group": "Sporting",
            "life_span": "10 - 12 years",
            "temperament": "Friendly, Energetic, Obedient, Intelligent, Protective, Trainable",
            "reference_image_id": "SkmRJl9VQ"
          }
        ],
        "id": "SkmRJl9VQ",
        "url": "https://cdn2.thedogapi.com/images/SkmRJl9VQ_390x256.jpg",
        "width": 1600,
        "height": 1264
      },
      "title": "",
      "like": 0
    },
    {
      "author": "은돌",
      "comments": [],
      "description": "",
      "id": "45b13569-cdf6-4a08-81ec-b8fc2d50edc5",
      "image": {
        "breeds": [
          {
            "weight": {
              "imperial": "80 - 150",
              "metric": "36 - 68"
            },
            "height": {
              "imperial": "27 - 29",
              "metric": "69 - 74"
            },
            "id": 18,
            "name": "Anatolian Shepherd Dog",
            "bred_for": "Livestock herding",
            "breed_group": "Working",
            "life_span": "11 - 13 years",
            "temperament": "Steady, Bold, Independent, Confident, Intelligent, Proud",
            "reference_image_id": "BJT0Jx5Nm"
          }
        ],
        "id": "BJT0Jx5Nm",
        "url": "https://cdn2.thedogapi.com/images/BJT0Jx5Nm_390x256.jpg",
        "width": 1216,
        "height": 1131
      },
      "title": "",
      "like": 0
    }
  ],
  "like": [
    {
      "id": "img3post3",
      "postId": "post3",
      "userId": "최은석"
    },
    {
      "id": "r1f_ll5VXpost15115",
      "postId": "post15115",
      "userId": "최은석"
    },
    {
      "id": "img10post10",
      "postId": "post10",
      "userId": "최은석"
    },
    {
      "id": "Bklnce5NXpost414",
      "postId": "post414",
      "userId": "최은석"
    },
    {
      "id": "img1post1533",
      "postId": "post1533",
      "userId": "최은석"
    },
    {
      "id": "img2post2",
      "postId": "post2",
      "userId": "최은석"
    },
    {
      "id": "img5post5",
      "postId": "post5",
      "userId": "최은석"
    },
    {
      "id": "img6post6",
      "postId": "post6",
      "userId": "최은석"
    },
    {
      "id": "img7post7",
      "postId": "post7",
      "userId": "최은석"
    },
    {
      "id": "img8post8",
      "postId": "post8",
      "userId": "최은석"
    },
    {
      "id": "img4post4",
      "postId": "post4",
      "userId": "최은석"
    }
  ]
}